{
  "request_id": "892375821146832896",
  "success": true,
  "message": "success",
  "code": 200,
  "data": {
    "date": "2026-03-17",
    "news": [
      "1、2月70城房价公布：北京、上海等10城新房价格环比上涨；二手房价格环比下跌城市降到66个，连续2个月减少；",
      "2、上海：调整商业用房购房贷款最低首付款比例为不低于30%；深圳：职工下月起可自愿申请提高公积金个人缴存比例；",
      "3、南京市人社局：优先批准职工在子女春秋假期间的带薪休假申请；",
      "4、国家医保局：2025年基本医保参保率巩固在95%，医保基金运行平稳；",
      "5、三部门印发指导意见：允许基层医疗卫生机构为符合条件的慢性病患者开具最长12周的长处方；",
      "6、国航、东航、南航发布维护旅客权益公告：国内机票买贵了可免费退，第三方平台加价可追责；",
      "7、OPPO、vivo官宣调价，渠道商透露：调价主要涉及3600元以下机型，涨幅在200至400元之间；",
      "8、第51届日内瓦国际发明展闭幕：中国代表团共获得90项金奖、95项银奖和52项铜奖；",
      "9、捐赠二战相册的埃文·凯尔宣布定居中国，他表示在中国找到“归属感”，未来将远程打理典当行生意；",
      "10、美对包括中国在内的60个经济体发起301调查，商务部回应：坚决反对，已向美方提出交涉；",
      "11、韩媒：高市早苗涉独岛言论引韩国抗议，韩国外交部表示将坚决严正应对；",
      "12、外媒：亚足联确认伊朗仍计划参加2026世界杯；5名在澳大利亚的伊朗女足队员决定放弃庇护申请，返回伊朗；",
      "13、英媒：霍尔木兹海峡14日通航船只数量首次降为零；特朗普被曝寻求本周组建霍尔木兹海峡“护航联盟”；",
      "14、外媒：伊朗首次用射程2000公里的“泥石”导弹打击以色列；美媒称以色列拦截弹药库存严重不足；",
      "15、外媒：伊朗新任最高领袖被曝正在莫斯科治疗，俄方对此不予置评；以色列总理发视频辟谣死亡传言，网友质疑视频由AI生成；"
    ],
    "weiyu": "【微语】贻误时机或张惶失措，就等于丧失一切。",
    "image": "https://file.alapi.cn/60s/202603171773690301.png",
    "audio": "https://file.alapi.cn/60s/audio/2026-03-17_377371340583032.mp3",
    "head_image": "https://file.alapi.cn/60s/202603171773690301_head.png"
  },
  "time": 1773718975,
  "usage": 0
}